{
  "generated_at": "2026-05-30T00:00:00Z",
  "scrape_date": "2026-05-30",
  "summary": {
    "macro_rising": 6,
    "macro_fading": 14,
    "saturated_niches": 0,
    "material_rising": 1
  },
  "macro_trends": [
    {
      "keyword": "mini",
      "flag": "Rising",
      "trend_pct": 115.2,
      "sentiment_score": 0.721,
      "composite_score": 83.06,
      "today_count": 88,
      "avg_7d": 40.9,
      "sparkline": [
        51,
        55,
        76,
        61,
        37,
        38,
        95
      ],
      "source_breakdown": {
        "retail": 12,
        "media": 76
      }
    },
    {
      "keyword": "retro",
      "flag": "Rising",
      "trend_pct": 204.3,
      "sentiment_score": 0.115,
      "composite_score": 23.49,
      "today_count": 14,
      "avg_7d": 4.6,
      "sparkline": [
        18,
        33,
        31,
        22,
        23,
        29,
        29
      ],
      "source_breakdown": {
        "retail": 0,
        "media": 14
      }
    },
    {
      "keyword": "crop",
      "flag": "Fading",
      "trend_pct": -46.2,
      "sentiment_score": 0.402,
      "composite_score": 18.57,
      "today_count": 49,
      "avg_7d": 91.1,
      "sparkline": [
        123,
        139,
        130,
        56,
        38,
        79,
        50
      ],
      "source_breakdown": {
        "retail": 2,
        "media": 47
      }
    },
    {
      "keyword": "metallic",
      "flag": "Rising",
      "trend_pct": 300.0,
      "sentiment_score": 0.033,
      "composite_score": 9.9,
      "today_count": 4,
      "avg_7d": 1.0,
      "sparkline": [
        0,
        0,
        0,
        0,
        1,
        1,
        4
      ],
      "source_breakdown": {
        "retail": 4,
        "media": 0
      }
    },
    {
      "keyword": "ruched",
      "flag": "Rising",
      "trend_pct": 69.5,
      "sentiment_score": 0.082,
      "composite_score": 5.7,
      "today_count": 10,
      "avg_7d": 5.9,
      "sparkline": [
        7,
        6,
        10,
        4,
        2,
        6,
        10
      ],
      "source_breakdown": {
        "retail": 10,
        "media": 0
      }
    },
    {
      "keyword": "wide leg",
      "flag": "Rising",
      "trend_pct": 55.8,
      "sentiment_score": 0.098,
      "composite_score": 5.47,
      "today_count": 12,
      "avg_7d": 7.7,
      "sparkline": [
        17,
        19,
        22,
        34,
        9,
        7,
        15
      ],
      "source_breakdown": {
        "retail": 12,
        "media": 0
      }
    },
    {
      "keyword": "halter",
      "flag": "Fading",
      "trend_pct": -62.0,
      "sentiment_score": 0.049,
      "composite_score": 3.04,
      "today_count": 6,
      "avg_7d": 15.8,
      "sparkline": [
        7,
        61,
        54,
        16,
        47,
        28,
        25
      ],
      "source_breakdown": {
        "retail": 6,
        "media": 0
      }
    },
    {
      "keyword": "midi",
      "flag": "Fading",
      "trend_pct": -29.9,
      "sentiment_score": 0.09,
      "composite_score": 2.69,
      "today_count": 11,
      "avg_7d": 15.7,
      "sparkline": [
        22,
        23,
        23,
        6,
        19,
        26,
        22
      ],
      "source_breakdown": {
        "retail": 10,
        "media": 1
      }
    },
    {
      "keyword": "stripe",
      "flag": "Fading",
      "trend_pct": -19.0,
      "sentiment_score": 0.139,
      "composite_score": 2.64,
      "today_count": 17,
      "avg_7d": 21.0,
      "sparkline": [
        25,
        48,
        37,
        25,
        14,
        15,
        17
      ],
      "source_breakdown": {
        "retail": 17,
        "media": 0
      }
    },
    {
      "keyword": "asymmetric",
      "flag": "Fading",
      "trend_pct": -62.6,
      "sentiment_score": 0.033,
      "composite_score": 2.07,
      "today_count": 4,
      "avg_7d": 10.7,
      "sparkline": [
        36,
        24,
        26,
        20,
        20,
        19,
        16
      ],
      "source_breakdown": {
        "retail": 4,
        "media": 0
      }
    },
    {
      "keyword": "cardigan",
      "flag": "Fading",
      "trend_pct": -40.6,
      "sentiment_score": 0.049,
      "composite_score": 1.99,
      "today_count": 6,
      "avg_7d": 10.1,
      "sparkline": [
        20,
        24,
        22,
        16,
        15,
        17,
        15
      ],
      "source_breakdown": {
        "retail": 6,
        "media": 0
      }
    },
    {
      "keyword": "smocked",
      "flag": "Rising",
      "trend_pct": 100.0,
      "sentiment_score": 0.016,
      "composite_score": 1.6,
      "today_count": 2,
      "avg_7d": 0.0,
      "sparkline": [
        0,
        0,
        0,
        0,
        0,
        0,
        2
      ],
      "source_breakdown": {
        "retail": 0,
        "media": 2
      }
    },
    {
      "keyword": "vest",
      "flag": "Staple",
      "trend_pct": -12.5,
      "sentiment_score": 0.115,
      "composite_score": 1.44,
      "today_count": 14,
      "avg_7d": 16.0,
      "sparkline": [
        41,
        30,
        38,
        26,
        54,
        53,
        37
      ],
      "source_breakdown": {
        "retail": 6,
        "media": 8
      }
    },
    {
      "keyword": "crochet",
      "flag": "Fading",
      "trend_pct": -50.8,
      "sentiment_score": 0.025,
      "composite_score": 1.27,
      "today_count": 3,
      "avg_7d": 6.1,
      "sparkline": [
        4,
        9,
        13,
        1,
        6,
        7,
        3
      ],
      "source_breakdown": {
        "retail": 1,
        "media": 2
      }
    },
    {
      "keyword": "maxi",
      "flag": "Staple",
      "trend_pct": -5.1,
      "sentiment_score": 0.197,
      "composite_score": 1.0,
      "today_count": 24,
      "avg_7d": 25.3,
      "sparkline": [
        44,
        36,
        37,
        16,
        39,
        51,
        35
      ],
      "source_breakdown": {
        "retail": 23,
        "media": 1
      }
    },
    {
      "keyword": "micro",
      "flag": "Fading",
      "trend_pct": -60.8,
      "sentiment_score": 0.016,
      "composite_score": 0.97,
      "today_count": 2,
      "avg_7d": 5.1,
      "sparkline": [
        6,
        8,
        6,
        7,
        2,
        3,
        2
      ],
      "source_breakdown": {
        "retail": 0,
        "media": 2
      }
    },
    {
      "keyword": "pleated",
      "flag": "Fading",
      "trend_pct": -24.5,
      "sentiment_score": 0.033,
      "composite_score": 0.81,
      "today_count": 4,
      "avg_7d": 5.3,
      "sparkline": [
        6,
        3,
        4,
        5,
        18,
        15,
        4
      ],
      "source_breakdown": {
        "retail": 4,
        "media": 0
      }
    },
    {
      "keyword": "oversized",
      "flag": "Fading",
      "trend_pct": -35.5,
      "sentiment_score": 0.016,
      "composite_score": 0.57,
      "today_count": 2,
      "avg_7d": 3.1,
      "sparkline": [
        5,
        9,
        7,
        10,
        6,
        8,
        6
      ],
      "source_breakdown": {
        "retail": 2,
        "media": 0
      }
    },
    {
      "keyword": "Y2K",
      "flag": "Fading",
      "trend_pct": -52.4,
      "sentiment_score": 0.008,
      "composite_score": 0.42,
      "today_count": 1,
      "avg_7d": 2.1,
      "sparkline": [
        3,
        2,
        2,
        1,
        2,
        2,
        1
      ],
      "source_breakdown": {
        "retail": 1,
        "media": 0
      }
    },
    {
      "keyword": "fringe",
      "flag": "Fading",
      "trend_pct": -50.0,
      "sentiment_score": 0.008,
      "composite_score": 0.4,
      "today_count": 1,
      "avg_7d": 2.0,
      "sparkline": [
        3,
        3,
        1,
        1,
        1,
        1,
        2
      ],
      "source_breakdown": {
        "retail": 0,
        "media": 1
      }
    },
    {
      "keyword": "workwear",
      "flag": "Fading",
      "trend_pct": -23.1,
      "sentiment_score": 0.016,
      "composite_score": 0.37,
      "today_count": 2,
      "avg_7d": 2.6,
      "sparkline": [
        3,
        5,
        5,
        4,
        4,
        4,
        4
      ],
      "source_breakdown": {
        "retail": 2,
        "media": 0
      }
    },
    {
      "keyword": "floral",
      "flag": "Staple",
      "trend_pct": 2.4,
      "sentiment_score": 0.139,
      "composite_score": 0.33,
      "today_count": 17,
      "avg_7d": 16.6,
      "sparkline": [
        31,
        47,
        50,
        36,
        55,
        65,
        46
      ],
      "source_breakdown": {
        "retail": 13,
        "media": 4
      }
    },
    {
      "keyword": "loafer",
      "flag": "Fading",
      "trend_pct": -23.1,
      "sentiment_score": 0.008,
      "composite_score": 0.18,
      "today_count": 1,
      "avg_7d": 1.3,
      "sparkline": [
        1,
        1,
        1,
        1,
        2,
        2,
        1
      ],
      "source_breakdown": {
        "retail": 1,
        "media": 0
      }
    },
    {
      "keyword": "loungewear",
      "flag": "Staple",
      "trend_pct": 0.0,
      "sentiment_score": 0.025,
      "composite_score": 0.0,
      "today_count": 3,
      "avg_7d": 3.0,
      "sparkline": [
        7,
        7,
        7,
        9,
        9,
        9,
        9
      ],
      "source_breakdown": {
        "retail": 3,
        "media": 0
      }
    },
    {
      "keyword": "strapless",
      "flag": "Staple",
      "trend_pct": 0.0,
      "sentiment_score": 0.025,
      "composite_score": 0.0,
      "today_count": 3,
      "avg_7d": 3.0,
      "sparkline": [
        3,
        3,
        3,
        0,
        0,
        3,
        3
      ],
      "source_breakdown": {
        "retail": 3,
        "media": 0
      }
    },
    {
      "keyword": "boho",
      "flag": "Staple",
      "trend_pct": 0.0,
      "sentiment_score": 0.016,
      "composite_score": 0.0,
      "today_count": 2,
      "avg_7d": 2.0,
      "sparkline": [
        1,
        1,
        1,
        1,
        3,
        3,
        3
      ],
      "source_breakdown": {
        "retail": 2,
        "media": 0
      }
    },
    {
      "keyword": "gorpcore",
      "flag": "Staple",
      "trend_pct": 0.0,
      "sentiment_score": 0.008,
      "composite_score": 0.0,
      "today_count": 1,
      "avg_7d": 1.0,
      "sparkline": [
        1,
        1,
        1,
        1,
        1,
        1,
        1
      ],
      "source_breakdown": {
        "retail": 1,
        "media": 0
      }
    },
    {
      "keyword": "2000s",
      "flag": "Staple",
      "trend_pct": 0.0,
      "sentiment_score": 0.008,
      "composite_score": 0.0,
      "today_count": 1,
      "avg_7d": 1.0,
      "sparkline": [
        0,
        0,
        0,
        0,
        1,
        1,
        1
      ],
      "source_breakdown": {
        "retail": 0,
        "media": 1
      }
    },
    {
      "keyword": "streetwear",
      "flag": "Staple",
      "trend_pct": 0.0,
      "sentiment_score": 0.008,
      "composite_score": 0.0,
      "today_count": 1,
      "avg_7d": 1.0,
      "sparkline": [
        1,
        3,
        5,
        9,
        5,
        5,
        7
      ],
      "source_breakdown": {
        "retail": 1,
        "media": 0
      }
    }
  ],
  "competitor_map": [
    {
      "keyword": "floral",
      "flag": "Niche",
      "saturation_score": 29,
      "trend_pct": 2.5,
      "site_count": 1,
      "total_suppliers": 9,
      "avg_7d": 28.3,
      "sparkline": [
        31,
        47,
        50,
        36,
        55,
        65,
        46
      ],
      "site_breakdown": {
        "fondmart": 29
      }
    },
    {
      "keyword": "slim fit",
      "flag": "Niche",
      "saturation_score": 23,
      "trend_pct": 40.2,
      "site_count": 1,
      "total_suppliers": 9,
      "avg_7d": 16.4,
      "sparkline": [
        20,
        18,
        15,
        15,
        18,
        10,
        23
      ],
      "site_breakdown": {
        "fondmart": 23
      }
    },
    {
      "keyword": "vest",
      "flag": "Niche",
      "saturation_score": 23,
      "trend_pct": 4.1,
      "site_count": 1,
      "total_suppliers": 9,
      "avg_7d": 22.1,
      "sparkline": [
        41,
        30,
        38,
        26,
        54,
        53,
        37
      ],
      "site_breakdown": {
        "fondmart": 23
      }
    },
    {
      "keyword": "cutout",
      "flag": "Niche",
      "saturation_score": 22,
      "trend_pct": 15.8,
      "site_count": 1,
      "total_suppliers": 9,
      "avg_7d": 19.0,
      "sparkline": [
        17,
        17,
        17,
        28,
        18,
        15,
        22
      ],
      "site_breakdown": {
        "fondmart": 22
      }
    },
    {
      "keyword": "halter",
      "flag": "Niche",
      "saturation_score": 19,
      "trend_pct": -12.4,
      "site_count": 1,
      "total_suppliers": 9,
      "avg_7d": 21.7,
      "sparkline": [
        7,
        61,
        54,
        16,
        47,
        28,
        25
      ],
      "site_breakdown": {
        "fondmart": 19
      }
    },
    {
      "keyword": "retro",
      "flag": "Growing",
      "saturation_score": 15,
      "trend_pct": -29.9,
      "site_count": 2,
      "total_suppliers": 9,
      "avg_7d": 21.4,
      "sparkline": [
        18,
        33,
        31,
        22,
        23,
        29,
        29
      ],
      "site_breakdown": {
        "fondmart": 13,
        "lightinthebox": 2
      }
    },
    {
      "keyword": "asymmetric",
      "flag": "Niche",
      "saturation_score": 12,
      "trend_pct": -19.5,
      "site_count": 1,
      "total_suppliers": 9,
      "avg_7d": 14.9,
      "sparkline": [
        36,
        24,
        26,
        20,
        20,
        19,
        16
      ],
      "site_breakdown": {
        "fondmart": 12
      }
    },
    {
      "keyword": "midi",
      "flag": "Growing",
      "saturation_score": 11,
      "trend_pct": 86.4,
      "site_count": 2,
      "total_suppliers": 9,
      "avg_7d": 5.9,
      "sparkline": [
        22,
        23,
        23,
        6,
        19,
        26,
        22
      ],
      "site_breakdown": {
        "fondmart": 9,
        "lightinthebox": 2
      }
    },
    {
      "keyword": "maxi",
      "flag": "Niche",
      "saturation_score": 11,
      "trend_pct": -20.9,
      "site_count": 1,
      "total_suppliers": 9,
      "avg_7d": 13.9,
      "sparkline": [
        44,
        36,
        37,
        16,
        39,
        51,
        35
      ],
      "site_breakdown": {
        "fondmart": 11
      }
    },
    {
      "keyword": "straight leg",
      "flag": "Growing",
      "saturation_score": 10,
      "trend_pct": 132.6,
      "site_count": 2,
      "total_suppliers": 9,
      "avg_7d": 4.3,
      "sparkline": [
        0,
        4,
        6,
        4,
        4,
        2,
        10
      ],
      "site_breakdown": {
        "fondmart": 6,
        "lightinthebox": 4
      }
    },
    {
      "keyword": "tube top",
      "flag": "Niche",
      "saturation_score": 9,
      "trend_pct": 30.4,
      "site_count": 1,
      "total_suppliers": 9,
      "avg_7d": 6.9,
      "sparkline": [
        3,
        5,
        7,
        11,
        6,
        7,
        9
      ],
      "site_breakdown": {
        "fondmart": 9
      }
    },
    {
      "keyword": "cardigan",
      "flag": "Niche",
      "saturation_score": 9,
      "trend_pct": 0.0,
      "site_count": 1,
      "total_suppliers": 9,
      "avg_7d": 9.0,
      "sparkline": [
        20,
        24,
        22,
        16,
        15,
        17,
        15
      ],
      "site_breakdown": {
        "fondmart": 9
      }
    },
    {
      "keyword": "mini",
      "flag": "Growing",
      "saturation_score": 7,
      "trend_pct": -40.2,
      "site_count": 2,
      "total_suppliers": 9,
      "avg_7d": 11.7,
      "sparkline": [
        51,
        55,
        76,
        61,
        37,
        38,
        95
      ],
      "site_breakdown": {
        "fondmart": 5,
        "lightinthebox": 2
      }
    },
    {
      "keyword": "loungewear",
      "flag": "Niche",
      "saturation_score": 6,
      "trend_pct": 22.4,
      "site_count": 1,
      "total_suppliers": 9,
      "avg_7d": 4.9,
      "sparkline": [
        7,
        7,
        7,
        9,
        9,
        9,
        9
      ],
      "site_breakdown": {
        "fondmart": 6
      }
    },
    {
      "keyword": "streetwear",
      "flag": "Niche",
      "saturation_score": 6,
      "trend_pct": 20.0,
      "site_count": 1,
      "total_suppliers": 9,
      "avg_7d": 5.0,
      "sparkline": [
        1,
        3,
        5,
        9,
        5,
        5,
        7
      ],
      "site_breakdown": {
        "lightinthebox": 6
      }
    },
    {
      "keyword": "off shoulder",
      "flag": "Niche",
      "saturation_score": 6,
      "trend_pct": 7.1,
      "site_count": 1,
      "total_suppliers": 9,
      "avg_7d": 5.6,
      "sparkline": [
        3,
        12,
        10,
        3,
        9,
        5,
        6
      ],
      "site_breakdown": {
        "fondmart": 6
      }
    },
    {
      "keyword": "oversized",
      "flag": "Niche",
      "saturation_score": 4,
      "trend_pct": 0.0,
      "site_count": 1,
      "total_suppliers": 9,
      "avg_7d": 4.0,
      "sparkline": [
        5,
        9,
        7,
        10,
        6,
        8,
        6
      ],
      "site_breakdown": {
        "fondmart": 4
      }
    },
    {
      "keyword": "wide leg",
      "flag": "Niche",
      "saturation_score": 3,
      "trend_pct": -70.3,
      "site_count": 1,
      "total_suppliers": 9,
      "avg_7d": 10.1,
      "sparkline": [
        17,
        19,
        22,
        34,
        9,
        7,
        15
      ],
      "site_breakdown": {
        "fondmart": 3
      }
    },
    {
      "keyword": "patchwork",
      "flag": "Niche",
      "saturation_score": 3,
      "trend_pct": 0.0,
      "site_count": 1,
      "total_suppliers": 9,
      "avg_7d": 3.0,
      "sparkline": [
        0,
        0,
        3,
        3,
        3,
        3,
        3
      ],
      "site_breakdown": {
        "fondmart": 3
      }
    },
    {
      "keyword": "workwear",
      "flag": "Niche",
      "saturation_score": 2,
      "trend_pct": 0.0,
      "site_count": 1,
      "total_suppliers": 9,
      "avg_7d": 2.0,
      "sparkline": [
        3,
        5,
        5,
        4,
        4,
        4,
        4
      ],
      "site_breakdown": {
        "lightinthebox": 2
      }
    },
    {
      "keyword": "minimalist",
      "flag": "Niche",
      "saturation_score": 2,
      "trend_pct": -60.0,
      "site_count": 1,
      "total_suppliers": 9,
      "avg_7d": 5.0,
      "sparkline": [
        7,
        1,
        8,
        0,
        1,
        3,
        2
      ],
      "site_breakdown": {
        "lightinthebox": 2
      }
    },
    {
      "keyword": "boho",
      "flag": "Niche",
      "saturation_score": 1,
      "trend_pct": 0.0,
      "site_count": 1,
      "total_suppliers": 9,
      "avg_7d": 1.0,
      "sparkline": [
        1,
        1,
        1,
        1,
        3,
        3,
        3
      ],
      "site_breakdown": {
        "fondmart": 1
      }
    },
    {
      "keyword": "fringe",
      "flag": "Niche",
      "saturation_score": 1,
      "trend_pct": 0.0,
      "site_count": 1,
      "total_suppliers": 9,
      "avg_7d": 1.0,
      "sparkline": [
        3,
        3,
        1,
        1,
        1,
        1,
        2
      ],
      "site_breakdown": {
        "fondmart": 1
      }
    },
    {
      "keyword": "corset",
      "flag": "Niche",
      "saturation_score": 1,
      "trend_pct": -47.4,
      "site_count": 1,
      "total_suppliers": 9,
      "avg_7d": 1.9,
      "sparkline": [
        1,
        3,
        5,
        4,
        3,
        1,
        1
      ],
      "site_breakdown": {
        "fondmart": 1
      }
    },
    {
      "keyword": "trench coat",
      "flag": "Niche",
      "saturation_score": 1,
      "trend_pct": 0.0,
      "site_count": 1,
      "total_suppliers": 9,
      "avg_7d": 1.0,
      "sparkline": [
        1,
        1,
        1,
        1,
        2,
        1,
        1
      ],
      "site_breakdown": {
        "fondmart": 1
      }
    },
    {
      "keyword": "blazer",
      "flag": "Niche",
      "saturation_score": 1,
      "trend_pct": -52.4,
      "site_count": 1,
      "total_suppliers": 9,
      "avg_7d": 2.1,
      "sparkline": [
        6,
        11,
        6,
        4,
        1,
        3,
        1
      ],
      "site_breakdown": {
        "fondmart": 1
      }
    },
    {
      "keyword": "crop",
      "flag": "Niche",
      "saturation_score": 1,
      "trend_pct": -83.3,
      "site_count": 1,
      "total_suppliers": 9,
      "avg_7d": 6.0,
      "sparkline": [
        123,
        139,
        130,
        56,
        38,
        79,
        50
      ],
      "site_breakdown": {
        "fondmart": 1
      }
    }
  ],
  "materials": [
    {
      "material": "chiffon",
      "flag": "Rising",
      "trend_pct": 58.4,
      "today_count": 16,
      "avg_7d": 10.1,
      "price_tier": "premium",
      "price_score": 2,
      "quality_signals": [
        "thin",
        "eco",
        "knitted"
      ],
      "sparkline": [
        7,
        5,
        7,
        6,
        20,
        21,
        16
      ],
      "source_breakdown": {
        "dropship": 6,
        "media": 0,
        "retail": 10
      }
    },
    {
      "material": "denim",
      "flag": "Staple",
      "trend_pct": 9.3,
      "today_count": 27,
      "avg_7d": 24.7,
      "price_tier": "mid",
      "price_score": 1,
      "quality_signals": [
        "thin",
        "eco",
        "knitted"
      ],
      "sparkline": [
        30,
        32,
        28,
        24,
        17,
        14,
        27
      ],
      "source_breakdown": {
        "dropship": 6,
        "media": 0,
        "retail": 21
      }
    },
    {
      "material": "wool",
      "flag": "Staple",
      "trend_pct": 0.0,
      "today_count": 39,
      "avg_7d": 39.0,
      "price_tier": "premium",
      "price_score": 2,
      "quality_signals": [
        "thin",
        "eco",
        "knitted"
      ],
      "sparkline": [
        39,
        39,
        39,
        39,
        39,
        39,
        39
      ],
      "source_breakdown": {
        "dropship": 39,
        "media": 0,
        "retail": 0
      }
    },
    {
      "material": "tweed",
      "flag": "Staple",
      "trend_pct": 0.0,
      "today_count": 3,
      "avg_7d": 3.0,
      "price_tier": "premium",
      "price_score": 2,
      "quality_signals": [
        "thin",
        "eco",
        "knitted"
      ],
      "sparkline": [
        3,
        3,
        3,
        3,
        3,
        3,
        3
      ],
      "source_breakdown": {
        "dropship": 3,
        "media": 0,
        "retail": 0
      }
    },
    {
      "material": "spandex",
      "flag": "Staple",
      "trend_pct": 0.0,
      "today_count": 2,
      "avg_7d": 2.0,
      "price_tier": "budget",
      "price_score": 0,
      "quality_signals": [
        "thin",
        "eco",
        "knitted"
      ],
      "sparkline": [
        0,
        2,
        2,
        2,
        0,
        2,
        2
      ],
      "source_breakdown": {
        "dropship": 2,
        "media": 0,
        "retail": 0
      }
    },
    {
      "material": "silk",
      "flag": "Staple",
      "trend_pct": -1.1,
      "today_count": 9,
      "avg_7d": 9.1,
      "price_tier": "premium",
      "price_score": 2,
      "quality_signals": [
        "thin",
        "eco",
        "knitted"
      ],
      "sparkline": [
        10,
        11,
        9,
        3,
        10,
        5,
        9
      ],
      "source_breakdown": {
        "dropship": 7,
        "media": 2,
        "retail": 0
      }
    },
    {
      "material": "mesh",
      "flag": "Staple",
      "trend_pct": -7.8,
      "today_count": 19,
      "avg_7d": 20.6,
      "price_tier": "budget",
      "price_score": 0,
      "quality_signals": [
        "thin",
        "eco",
        "knitted"
      ],
      "sparkline": [
        20,
        21,
        22,
        22,
        13,
        13,
        19
      ],
      "source_breakdown": {
        "dropship": 17,
        "media": 0,
        "retail": 2
      }
    },
    {
      "material": "tulle",
      "flag": "Staple",
      "trend_pct": -9.1,
      "today_count": 5,
      "avg_7d": 5.5,
      "price_tier": "premium",
      "price_score": 2,
      "quality_signals": [
        "thin",
        "eco",
        "knitted"
      ],
      "sparkline": [
        5,
        5,
        5,
        7,
        4,
        0,
        5
      ],
      "source_breakdown": {
        "dropship": 5,
        "media": 0,
        "retail": 0
      }
    },
    {
      "material": "knit",
      "flag": "Staple",
      "trend_pct": -13.5,
      "today_count": 34,
      "avg_7d": 39.3,
      "price_tier": "mid",
      "price_score": 1,
      "quality_signals": [
        "thin",
        "eco",
        "knitted"
      ],
      "sparkline": [
        40,
        57,
        40,
        29,
        31,
        41,
        34
      ],
      "source_breakdown": {
        "dropship": 26,
        "media": 0,
        "retail": 8
      }
    },
    {
      "material": "linen",
      "flag": "Fading",
      "trend_pct": -15.7,
      "today_count": 29,
      "avg_7d": 34.4,
      "price_tier": "mid",
      "price_score": 1,
      "quality_signals": [
        "thin",
        "eco",
        "knitted"
      ],
      "sparkline": [
        21,
        43,
        36,
        40,
        32,
        31,
        29
      ],
      "source_breakdown": {
        "dropship": 27,
        "media": 0,
        "retail": 2
      }
    },
    {
      "material": "cotton",
      "flag": "Fading",
      "trend_pct": -22.0,
      "today_count": 44,
      "avg_7d": 56.4,
      "price_tier": "mid",
      "price_score": 1,
      "quality_signals": [
        "thin",
        "eco",
        "knitted"
      ],
      "sparkline": [
        53,
        54,
        58,
        73,
        49,
        58,
        44
      ],
      "source_breakdown": {
        "dropship": 42,
        "media": 0,
        "retail": 2
      }
    },
    {
      "material": "jersey",
      "flag": "Fading",
      "trend_pct": -42.9,
      "today_count": 2,
      "avg_7d": 3.5,
      "price_tier": "mid",
      "price_score": 1,
      "quality_signals": [
        "thin",
        "eco",
        "knitted"
      ],
      "sparkline": [
        2,
        2,
        1,
        1,
        9,
        6,
        2
      ],
      "source_breakdown": {
        "dropship": 0,
        "media": 0,
        "retail": 2
      }
    },
    {
      "material": "satin",
      "flag": "Fading",
      "trend_pct": -58.0,
      "today_count": 6,
      "avg_7d": 14.3,
      "price_tier": "premium",
      "price_score": 2,
      "quality_signals": [
        "thin",
        "eco",
        "knitted"
      ],
      "sparkline": [
        16,
        12,
        16,
        19,
        17,
        9,
        6
      ],
      "source_breakdown": {
        "dropship": 0,
        "media": 2,
        "retail": 4
      }
    },
    {
      "material": "fleece",
      "flag": "Fading",
      "trend_pct": -66.7,
      "today_count": 1,
      "avg_7d": 3.0,
      "price_tier": "mid",
      "price_score": 1,
      "quality_signals": [
        "thin",
        "eco",
        "knitted"
      ],
      "sparkline": [
        4,
        6,
        4,
        1,
        1,
        1,
        1
      ],
      "source_breakdown": {
        "dropship": 0,
        "media": 0,
        "retail": 1
      }
    },
    {
      "material": "velvet",
      "flag": "Fading",
      "trend_pct": -74.4,
      "today_count": 1,
      "avg_7d": 3.9,
      "price_tier": "premium",
      "price_score": 2,
      "quality_signals": [
        "thin",
        "eco",
        "knitted"
      ],
      "sparkline": [
        4,
        4,
        4,
        3,
        5,
        3,
        1
      ],
      "source_breakdown": {
        "dropship": 0,
        "media": 1,
        "retail": 0
      }
    },
    {
      "material": "bamboo",
      "flag": "Fading",
      "trend_pct": -75.0,
      "today_count": 1,
      "avg_7d": 4.0,
      "price_tier": "mid",
      "price_score": 1,
      "quality_signals": [
        "thin",
        "eco",
        "knitted"
      ],
      "sparkline": [
        0,
        0,
        0,
        4,
        0,
        0,
        1
      ],
      "source_breakdown": {
        "dropship": 0,
        "media": 1,
        "retail": 0
      }
    }
  ]
}